fastapi_mongo_logger/__init__.py
fastapi_mongo_logger/decorators.py
fastapi_mongo_logger/logger.py
fastapi_mongo_logger/middleware.py
fastapi_mongo_logger_mateoramos-1.0.7.dist-info/METADATA
fastapi_mongo_logger_mateoramos-1.0.7.dist-info/WHEEL
fastapi_mongo_logger_mateoramos-1.0.7.dist-info/licenses/LICENSE
fastapi_mongo_logger_mateoramos-1.0.7.dist-info/RECORD
