Metadata-Version: 2.4
Name: fastapi-mongo-logger-mateoramos
Version: 1.0.7
Summary: FastAPI MongoDB logging package for endpoints and general logging
License: MIT
License-File: LICENSE
Keywords: fastapi,mongodb,logging,middleware,async,jwt
Author: Mateo Ramos
Author-email: mateoramos1997@gmail.com
Requires-Python: >=3.7,<4.0
Classifier: Development Status :: 4 - Beta
Classifier: Framework :: FastAPI
Classifier: Intended Audience :: Developers
Classifier: License :: OSI Approved :: MIT License
Classifier: Operating System :: OS Independent
Classifier: Programming Language :: Python :: 3
Classifier: Programming Language :: Python :: 3.7
Classifier: Programming Language :: Python :: 3.8
Classifier: Programming Language :: Python :: 3.9
Classifier: Programming Language :: Python :: 3.10
Classifier: Programming Language :: Python :: 3.11
Classifier: Programming Language :: Python :: 3.12
Classifier: Programming Language :: Python :: 3.13
Classifier: Programming Language :: Python :: 3.14
Classifier: Topic :: Internet :: WWW/HTTP :: HTTP Servers
Classifier: Topic :: Software Development :: Libraries :: Python Modules
Classifier: Topic :: System :: Logging
Requires-Dist: PyJWT (>=2.0.0)
Requires-Dist: fastapi (>=0.68.0)
Requires-Dist: motor (>=3.0.0)
Requires-Dist: pydantic (>=1.8.0)
Requires-Dist: pymongo (>=4.0.0)
Project-URL: Bug Reports, https://github.com/mateoramos97/fastapi-mongo-logs/issues
Project-URL: Homepage, https://github.com/mateoramos97/fastapi-mongo-logs
Project-URL: Repository, https://github.com/mateoramos97/fastapi-mongo-logs
